cvslicer/CVSlicer.py
cvslicer/__init__.py
cvslicer/get_image_size.py
cvslicer-1.0.1.dist-info/LICENSE
cvslicer-1.0.1.dist-info/METADATA
cvslicer-1.0.1.dist-info/WHEEL
cvslicer-1.0.1.dist-info/top_level.txt
cvslicer-1.0.1.dist-info/RECORD
