Metadata-Version: 2.1
Name: cvslicer
Version: 1.0.1
Summary: CV Slicer
Home-page: https://github.com/JY-Quek/CVSlicer
Author: Quek JY
License: UNKNOWN
Keywords: slice,crop,smart,image recognition,object,opencv,cv,vision
Platform: any
License-File: LICENSE
Requires-Dist: numpy
Requires-Dist: Pillow
Provides-Extra: extra
Requires-Dist: opencv-python ; extra == 'extra'
